event_ami_gnew/__init__.py
event_ami_gnew/entities.py
event_ami_gnew/events.py
event_ami_gnew/managers.py
event_ami_asterisk-0.1.0.dist-info/LICENSE
event_ami_asterisk-0.1.0.dist-info/METADATA
event_ami_asterisk-0.1.0.dist-info/WHEEL
event_ami_asterisk-0.1.0.dist-info/top_level.txt
event_ami_asterisk-0.1.0.dist-info/RECORD
