Metadata-Version: 2.1
Name: event-ami-asterisk
Version: 0.1.0
Summary: Manager for Asterisk events received from AMI
Home-page: UNKNOWN
Author: Tatianno Alves
Author-email: tferreiraalves@gmail.com
License: MIT License
Keywords: asterisk ami gnew
Platform: UNKNOWN
Requires-Dist: wheel
